{
  "navbar": {
    "image": "assets/UI Images/Fusion360SolidNavbar.png",
    "description": "Fusion 360 Design workspace Solid environment navbar",
    "dimensions": {
      "width": 1567,
      "height": 300,
      "note": "Approximate dimensions for position calculations"
    }
  },
  "components": {
    "workspaceDropdown": {
      "id": "workspace-dropdown",
      "label": "DESIGN",
      "position": { "x": 4.5, "y": 12, "width": 5, "height": 8 },
      "description": "Workspace selection dropdown (Design, Render, Animation, etc.)"
    },
    "environmentTabs": {
      "solid": {
        "id": "env-solid",
        "label": "SOLID",
        "position": { "x": 11, "y": 3, "width": 3.5, "height": 5 },
        "description": "Solid modeling environment tab",
        "active": true
      },
      "surface": {
        "id": "env-surface",
        "label": "SURFACE",
        "position": { "x": 16, "y": 3, "width": 4.5, "height": 5 },
        "description": "Surface modeling environment tab"
      },
      "mesh": {
        "id": "env-mesh",
        "label": "MESH",
        "position": { "x": 22, "y": 3, "width": 3, "height": 5 },
        "description": "Mesh modeling environment tab"
      },
      "sheetMetal": {
        "id": "env-sheet-metal",
        "label": "SHEET METAL",
        "position": { "x": 26, "y": 3, "width": 6, "height": 5 },
        "description": "Sheet metal environment tab"
      },
      "plastic": {
        "id": "env-plastic",
        "label": "PLASTIC",
        "position": { "x": 34, "y": 3, "width": 4, "height": 5 },
        "description": "Plastic modeling environment tab"
      },
      "utilities": {
        "id": "env-utilities",
        "label": "UTILITIES",
        "position": { "x": 40, "y": 3, "width": 4.5, "height": 5 },
        "description": "Utilities environment tab"
      }
    },
    "toolbarGroups": {
      "create": {
        "id": "toolbar-create",
        "label": "CREATE",
        "position": { "x": 10, "y": 12, "width": 10, "height": 18 },
        "description": "Create tools dropdown (New Component, Sketch, Extrude, etc.)",
        "tools": [
          { "id": "new-component", "icon": "component", "position": { "x": 10, "y": 12 } },
          { "id": "create-sketch", "icon": "sketch", "position": { "x": 13.5, "y": 12 } },
          { "id": "extrude", "icon": "extrude", "position": { "x": 17, "y": 12 } },
          { "id": "revolve", "icon": "revolve", "position": { "x": 20, "y": 12 } }
        ]
      },
      "modify": {
        "id": "toolbar-modify",
        "label": "MODIFY",
        "position": { "x": 32, "y": 12, "width": 14, "height": 18 },
        "description": "Modify tools dropdown (Fillet, Chamfer, Shell, etc.)",
        "tools": [
          { "id": "press-pull", "icon": "press-pull", "position": { "x": 32, "y": 12 } },
          { "id": "fillet", "icon": "fillet", "position": { "x": 35, "y": 12 } },
          { "id": "chamfer", "icon": "chamfer", "position": { "x": 38, "y": 12 } },
          { "id": "shell", "icon": "shell", "position": { "x": 41, "y": 12 } },
          { "id": "move-copy", "icon": "move", "position": { "x": 44, "y": 12 } }
        ]
      },
      "configure": {
        "id": "toolbar-configure",
        "label": "CONFIGURE",
        "position": { "x": 50, "y": 12, "width": 7, "height": 18 },
        "description": "Configuration tools"
      },
      "construct": {
        "id": "toolbar-construct",
        "label": "CONSTRUCT",
        "position": { "x": 58, "y": 12, "width": 6, "height": 18 },
        "description": "Construction geometry tools (Planes, Axes, Points)"
      },
      "inspect": {
        "id": "toolbar-inspect",
        "label": "INSPECT",
        "position": { "x": 65, "y": 12, "width": 5, "height": 18 },
        "description": "Inspection and measurement tools"
      },
      "insert": {
        "id": "toolbar-insert",
        "label": "INSERT",
        "position": { "x": 72, "y": 12, "width": 8, "height": 18 },
        "description": "Insert external files and components"
      },
      "assemble": {
        "id": "toolbar-assemble",
        "label": "ASSEMBLE",
        "position": { "x": 82, "y": 12, "width": 5, "height": 18 },
        "description": "Assembly tools (Joint, As-built Joint, etc.)"
      },
      "select": {
        "id": "toolbar-select",
        "label": "SELECT",
        "position": { "x": 89, "y": 12, "width": 4, "height": 18 },
        "description": "Selection mode and filters"
      }
    },
    "browser": {
      "id": "browser-panel",
      "label": "BROWSER",
      "position": { "x": 1, "y": 40, "width": 15, "height": 50 },
      "description": "Model browser tree showing document structure",
      "items": {
        "documentSettings": { "position": { "x": 5, "y": 47, "width": 10, "height": 3 } },
        "namedViews": { "position": { "x": 5, "y": 51, "width": 8, "height": 3 } },
        "origin": { "position": { "x": 5, "y": 55, "width": 5, "height": 3 } },
        "bodies": { "position": { "x": 5, "y": 59, "width": 5, "height": 3 } },
        "sketches": { "position": { "x": 5, "y": 63, "width": 7, "height": 3 } }
      }
    },
    "viewCube": {
      "id": "view-cube",
      "label": "ViewCube",
      "position": { "x": 90, "y": 55, "width": 8, "height": 12 },
      "description": "3D navigation ViewCube"
    }
  },
  "commonActions": {
    "createSketch": {
      "path": ["toolbarGroups.create.tools[1]"],
      "positions": [{ "x": 13.5, "y": 12, "width": 3, "height": 8 }],
      "label": "Create Sketch"
    },
    "extrude": {
      "path": ["toolbarGroups.create.tools[2]"],
      "positions": [{ "x": 17, "y": 12, "width": 3, "height": 8 }],
      "label": "Extrude"
    },
    "fillet": {
      "path": ["toolbarGroups.modify.tools[1]"],
      "positions": [{ "x": 35, "y": 12, "width": 3, "height": 8 }],
      "label": "Fillet"
    },
    "switchToSolid": {
      "path": ["environmentTabs.solid"],
      "positions": [{ "x": 11, "y": 3, "width": 3.5, "height": 5 }],
      "label": "Switch to Solid"
    },
    "switchToSurface": {
      "path": ["environmentTabs.surface"],
      "positions": [{ "x": 16, "y": 3, "width": 4.5, "height": 5 }],
      "label": "Switch to Surface"
    },
    "finishSketch": {
      "path": ["sketchToolbar.finishSketch"],
      "positions": [{ "x": 85, "y": 12, "width": 4, "height": 5 }],
      "label": "Finish Sketch",
      "note": "Only visible when in sketch mode"
    }
  }
}
